config2py/__init__.py
config2py/base.py
config2py/errors.py
config2py/s_configparser.py
config2py/sync_store.py
config2py/tools.py
config2py/util.py
config2py/scrap/__init__.py
config2py/tests/__init__.py
config2py/tests/test_sync_store.py
config2py/tests/test_tools.py
config2py/tests/utils_for_testing.py
config2py-0.1.45.dist-info/METADATA
config2py-0.1.45.dist-info/WHEEL
config2py-0.1.45.dist-info/licenses/LICENSE
config2py-0.1.45.dist-info/RECORD
