Metadata-Version: 2.4
Name: config2py
Version: 0.1.45
Summary: Simplified reading and writing configurations from various sources and formats
Project-URL: Homepage, https://github.com/i2mint/config2py
License: Apache-2.0
License-File: LICENSE
Requires-Python: >=3.10
Requires-Dist: dol
Requires-Dist: i2
Requires-Dist: importlib-resources; python_version < '3.9'
Provides-Extra: dev
Requires-Dist: pytest-cov>=4.0; extra == 'dev'
Requires-Dist: pytest>=7.0; extra == 'dev'
Requires-Dist: ruff>=0.1.0; extra == 'dev'
Provides-Extra: docs
Requires-Dist: sphinx-rtd-theme>=1.0; extra == 'docs'
Requires-Dist: sphinx>=6.0; extra == 'docs'
